pychanasync/__init__.py
pychanasync/chan.py
pychanasync/errors.py
pychanasync-1.0.0.dist-info/licenses/LICENSE
pychanasync-1.0.0.dist-info/METADATA
pychanasync-1.0.0.dist-info/WHEEL
pychanasync-1.0.0.dist-info/top_level.txt
pychanasync-1.0.0.dist-info/RECORD
