Metadata-Version: 2.4
Name: pychanasync
Version: 1.0.0
Summary: pychanasync is a lightweight python package which brings Go-style channels to python's asyncio concurrency world. It is an async-channel implementation, providing a channel shaped tool for channel shaped problems.
Author-email: Gwalisam Matthew <gwalisammatthew2@gmail.com>
License: MIT
Project-URL: homepage, https://gwali-1.github.io/PY_CHANNELS_ASYNC
Project-URL: repository, https://github.com/Gwali-1/PY_CHANNELS_ASYNC
Project-URL: Issues, https://github.com/Gwali-1/PY_CHANNELS_ASYNC/issues
Project-URL: documentation, https://gwali-1.github.io/PY_CHANNELS_ASYNC
Keywords: async,channel,concurrency,non-blocking,python,asyncio
Classifier: Development Status :: 3 - Alpha
Classifier: Intended Audience :: Developers
Classifier: License :: OSI Approved :: MIT License
Classifier: Programming Language :: Python :: 3
Classifier: Programming Language :: Python :: 3.11
Classifier: Programming Language :: Python :: 3.12
Classifier: Topic :: Software Development :: Libraries
Requires-Python: >=3.11
License-File: LICENSE
Dynamic: license-file
